roblox_api_checker/__init__.py
roblox_api_checker/cli.py
roblox_api_checker/server.py
roblox_api_status-1.dist-info/METADATA
roblox_api_status-1.dist-info/WHEEL
roblox_api_status-1.dist-info/entry_points.txt
roblox_api_status-1.dist-info/top_level.txt
roblox_api_status-1.dist-info/RECORD
