Metadata-Version: 2.1
Name: roblox-api-status
Version: 1
Summary: Lame roblox api checker based on response code.
Home-page: https://github.com/dumb-stuff/Meta-search
Author: Rukchad Wongprayoon
Author-email: contact@biomooping.tk
License: MIT
Keywords: Tools
Platform: UNKNOWN
Requires-Dist: flask
Requires-Dist: requests
